LICENSE
README.md
pyproject.toml
mcp_openapi_proxy/__init__.py
mcp_openapi_proxy/handlers.py
mcp_openapi_proxy/logging_setup.py
mcp_openapi_proxy/openapi.py
mcp_openapi_proxy/server_fastmcp.py
mcp_openapi_proxy/server_lowlevel.py
mcp_openapi_proxy/types.py
mcp_openapi_proxy/utils.py
mcp_openapi_proxy_swagger_auth.egg-info/PKG-INFO
mcp_openapi_proxy_swagger_auth.egg-info/SOURCES.txt
mcp_openapi_proxy_swagger_auth.egg-info/dependency_links.txt
mcp_openapi_proxy_swagger_auth.egg-info/entry_points.txt
mcp_openapi_proxy_swagger_auth.egg-info/requires.txt
mcp_openapi_proxy_swagger_auth.egg-info/top_level.txt