Metadata-Version: 2.4
Name: mcp-openapi-proxy-swagger-auth
Version: 0.1.0
Summary: MCP server for exposing OpenAPI specifications as MCP tools.
Author-email: Matthew Hand <matthewhandau@gmail.com>
Requires-Python: >=3.10
License-File: LICENSE
Requires-Dist: mcp[cli]>=1.2.0
Requires-Dist: python-dotenv>=1.0.1
Requires-Dist: requests>=2.25.0
Requires-Dist: fastapi>=0.100.0
Requires-Dist: pydantic>=2.0
Requires-Dist: prance>=23.6.21.0
Requires-Dist: openapi-spec-validator>=0.7.1
Requires-Dist: jmespath>=1.0.1
Dynamic: license-file
